{
  "size": {
    "width": 2500,
    "height": 1686
  },
  "selected": true,
  "name": "state-edit-menu",
  "chatBarText": "編集中",
  "areas": [
    {
      "bounds": {
        "x": 0,
        "y": 0,
        "width": 1250,
        "height": 843
      },
      "action": {
        "type": "postback",
        "label": "買うもの",
        "data": "menu=edit:section:2345678901",
        "displayText": "買うものを編集する"
      }
    },
    {
      "bounds": {
        "x": 1250,
        "y": 0,
        "width": 1250,
        "height": 843
      },
      "action": {
        "type": "postback",
        "label": "やること",
        "data": "menu=edit:section:3456789012",
        "displayText": "やることを編集する"
      }
    },
    {
      "bounds": {
        "x": 0,
        "y": 843,
        "width": 1250,
        "height": 843
      },
      "action": {
        "type": "message",
        "label": "キャンセル",
        "text": "キャンセル"
      }
    },
    {
      "bounds": {
        "x": 1250,
        "y": 843,
        "width": 1250,
        "height": 843
      },
      "action": {
        "type": "postback",
        "label": "一覧を見る",
        "data": "menu=list-preview",
        "displayText": "一覧を見直す"
      }
    }
  ]
}
